tesla_powerwall_controller/__init__.py
tesla_powerwall_controller/__main__.py
tesla_powerwall_controller-0.4.dist-info/LICENSE
tesla_powerwall_controller-0.4.dist-info/METADATA
tesla_powerwall_controller-0.4.dist-info/WHEEL
tesla_powerwall_controller-0.4.dist-info/top_level.txt
tesla_powerwall_controller-0.4.dist-info/RECORD
