Metadata-Version: 2.1
Name: tesla-powerwall-controller
Version: 0.4
Summary: Python controller for reading tesla powerwall status
Home-page: https://github.com/samtherussell/tesla-powerwall-controller
Author: samtherussell
License: UNKNOWN
Platform: UNKNOWN
Classifier: Programming Language :: Python :: 3
Classifier: License :: OSI Approved :: MIT License
Classifier: Operating System :: OS Independent
Requires-Dist: requests
